README
maildir_featurizer.py
setup.py
maildir_featurizer.egg-info/PKG-INFO
maildir_featurizer.egg-info/SOURCES.txt
maildir_featurizer.egg-info/dependency_links.txt
maildir_featurizer.egg-info/entry_points.txt
maildir_featurizer.egg-info/pbr.json
maildir_featurizer.egg-info/top_level.txt