Metadata-Version: 1.1
Name: maildir-featurizer
Version: 0.1
Summary: Quickly featurize a maildir
Home-page: https://thomaslevine.com
Author: Thomas Levine
Author-email: _@thomaslevine.com
License: AGPL
Platform: UNKNOWN
Classifier: Programming Language :: Python :: 3.4
